wow_ai_ml/__init__.py
wow_ai_ml/api.py
wow_ai_ml/default_configs/Dockerfile
wow_ai_ml/default_configs/README.md
wow_ai_ml/default_configs/_wsgi.py.tmpl
wow_ai_ml/default_configs/docker-compose.yml
wow_ai_ml/default_configs/requirements.txt
wow_ai_ml/exceptions.py
wow_ai_ml/helpers.py
wow_ai_ml/model.py
wow_ai_ml/server.py
wow_ai_ml/templates/preview.html
wow_ai_ml/utils.py
wow_ai_ml-0.3.1.dist-info/METADATA
wow_ai_ml-0.3.1.dist-info/WHEEL
wow_ai_ml-0.3.1.dist-info/RECORD
