Metadata-Version: 2.1
Name: wow_ai_ml
Version: 0.3.1
Summary: 
Author: TonyShark
Author-email: quoi@wow-ai.inc
Requires-Python: >=3.8,<4.0
Classifier: Programming Language :: Python :: 3
Classifier: Programming Language :: Python :: 3.8
Classifier: Programming Language :: Python :: 3.9
Classifier: Programming Language :: Python :: 3.10
Classifier: Programming Language :: Python :: 3.11
